pyDOID/__init__.py
pyDOID/owl.py
pyDOID/repo.py
pyDOID/util.py
pyDOID-0.1.6.dist-info/LICENSE
pyDOID-0.1.6.dist-info/METADATA
pyDOID-0.1.6.dist-info/WHEEL
pyDOID-0.1.6.dist-info/top_level.txt
pyDOID-0.1.6.dist-info/RECORD
