Metadata-Version: 2.1
Name: pyDOID
Version: 0.1.6
Summary: Utilities for managing the Human Disease Ontology.
Home-page: https://github.com/allenbaron/pyDOID
Author: J. Allen Baron
Author-email: jabaron.phd@gmail.com
Project-URL: Bug Tracker, https://github.com/allenbaron/pyDOID/issues
Classifier: Programming Language :: Python :: 3
Classifier: License :: OSI Approved :: MIT License
Classifier: Operating System :: OS Independent
Requires-Python: >=3.6
License-File: LICENSE
Requires-Dist: GitPython
Requires-Dist: rdflib
Requires-Dist: pandas
Requires-Dist: tqdm
